odoo/addons/project_coordinator/README.rst
odoo/addons/project_coordinator/__init__.py
odoo/addons/project_coordinator/__manifest__.py
odoo/addons/project_coordinator/i18n/ca_ES.po
odoo/addons/project_coordinator/i18n/es.po
odoo/addons/project_coordinator/models/__init__.py
odoo/addons/project_coordinator/models/project_project.py
odoo/addons/project_coordinator/models/project_task.py
odoo/addons/project_coordinator/readme/CONTRIBUTORS.md
odoo/addons/project_coordinator/readme/DESCRIPTION.md
odoo/addons/project_coordinator/readme/USAGE.md
odoo/addons/project_coordinator/static/description/icon.png
odoo/addons/project_coordinator/static/description/index.html
odoo/addons/project_coordinator/tests/__init__.py
odoo/addons/project_coordinator/tests/test_project_coordinator.py
odoo/addons/project_coordinator/views/project_task_views.xml
odoo/addons/project_coordinator/views/project_views.xml
odoo_addon_project_coordinator-18.0.1.0.0.1.dist-info/METADATA
odoo_addon_project_coordinator-18.0.1.0.0.1.dist-info/WHEEL
odoo_addon_project_coordinator-18.0.1.0.0.1.dist-info/top_level.txt
odoo_addon_project_coordinator-18.0.1.0.0.1.dist-info/RECORD
